{
  "uid": "bdag-operator-cockpit",
  "title": "BDAG Operator Cockpit",
  "tags": [
    "blockdag",
    "mining",
    "provisioned"
  ],
  "timezone": "browser",
  "schemaVersion": 39,
  "version": 1,
  "refresh": "30s",
  "time": {
    "from": "now-6h",
    "to": "now"
  },
  "timepicker": {
    "refresh_intervals": [
      "10s",
      "30s",
      "1m",
      "5m",
      "15m"
    ],
    "time_options": [
      "1h",
      "6h",
      "12h",
      "24h",
      "3d",
      "7d",
      "30d"
    ]
  },
  "editable": false,
  "annotations": {
    "list": [
      {
        "builtIn": 1,
        "datasource": {
          "type": "grafana",
          "uid": "-- Grafana --"
        },
        "enable": true,
        "hide": true,
        "iconColor": "rgba(0, 211, 255, 1)",
        "name": "Annotations & Alerts",
        "type": "dashboard"
      }
    ]
  },
  "links": [
    {
      "title": "Operator Cockpit",
      "url": "/d/bdag-operator-cockpit/bdag-operator-cockpit",
      "targetBlank": false,
      "type": "link"
    },
    {
      "title": "Accepted Work Share",
      "url": "/d/bdag-work-share/bdag-accepted-work-share",
      "targetBlank": false,
      "type": "link"
    },
    {
      "title": "Miner Freshness",
      "url": "/d/bdag-miner-freshness/bdag-miner-freshness",
      "targetBlank": false,
      "type": "link"
    },
    {
      "title": "Observed Peer IPs",
      "url": "/d/bdag-observed-peers/bdag-observed-peer-ips",
      "targetBlank": false,
      "type": "link"
    },
    {
      "title": "Template Fan-In",
      "url": "/d/bdag-template-fan-in/bdag-template-fan-in",
      "targetBlank": false,
      "type": "link"
    },
    {
      "title": "Old Repair Dashboard",
      "url": "http://127.0.0.1:8088",
      "targetBlank": true,
      "type": "link"
    }
  ],
  "panels": [
    {
      "id": 1,
      "type": "stat",
      "title": "Mining State",
      "datasource": {
        "type": "prometheus",
        "uid": "bdag-prometheus"
      },
      "gridPos": {
        "x": 0,
        "y": 0,
        "w": 3,
        "h": 3
      },
      "targets": [
        {
          "expr": "max(bdag_stack_status)",
          "legendFormat": "",
          "refId": "A"
        }
      ],
      "fieldConfig": {
        "defaults": {
          "unit": "short",
          "custom": {},
          "color": {
            "mode": "thresholds"
          },
          "thresholds": {
            "mode": "absolute",
            "steps": [
              {
                "value": null,
                "color": "red"
              },
              {
                "value": 0.5,
                "color": "orange"
              },
              {
                "value": 1,
                "color": "green"
              }
            ]
          },
          "noValue": "-"
        },
        "overrides": []
      },
      "options": {
        "colorMode": "background",
        "graphMode": "none",
        "justifyMode": "center",
        "orientation": "auto",
        "reduceOptions": {
          "calcs": [
            "lastNotNull"
          ],
          "fields": "",
          "values": false
        },
        "textMode": "value_and_name",
        "wideLayout": true
      }
    },
    {
      "id": 2,
      "type": "stat",
      "title": "USD / Hour",
      "datasource": {
        "type": "prometheus",
        "uid": "bdag-prometheus"
      },
      "gridPos": {
        "x": 3,
        "y": 0,
        "w": 3,
        "h": 3
      },
      "targets": [
        {
          "expr": "bdag_wallet_recent_usd_per_hour",
          "legendFormat": "",
          "refId": "A"
        }
      ],
      "fieldConfig": {
        "defaults": {
          "unit": "currencyUSD",
          "custom": {},
          "color": {
            "mode": "thresholds"
          },
          "decimals": 2,
          "thresholds": {
            "mode": "absolute",
            "steps": [
              {
                "value": null,
                "color": "red"
              },
              {
                "value": 0.01,
                "color": "green"
              }
            ]
          },
          "noValue": "-"
        },
        "overrides": []
      },
      "options": {
        "colorMode": "background",
        "graphMode": "none",
        "justifyMode": "center",
        "orientation": "auto",
        "reduceOptions": {
          "calcs": [
            "lastNotNull"
          ],
          "fields": "",
          "values": false
        },
        "textMode": "value_and_name",
        "wideLayout": true
      }
    },
    {
      "id": 3,
      "type": "stat",
      "title": "24h USD",
      "datasource": {
        "type": "prometheus",
        "uid": "bdag-prometheus"
      },
      "gridPos": {
        "x": 6,
        "y": 0,
        "w": 3,
        "h": 3
      },
      "targets": [
        {
          "expr": "bdag_wallet_24h_usd",
          "legendFormat": "",
          "refId": "A"
        }
      ],
      "fieldConfig": {
        "defaults": {
          "unit": "currencyUSD",
          "custom": {},
          "color": {
            "mode": "thresholds"
          },
          "decimals": 2,
          "noValue": "-"
        },
        "overrides": []
      },
      "options": {
        "colorMode": "background",
        "graphMode": "none",
        "justifyMode": "center",
        "orientation": "auto",
        "reduceOptions": {
          "calcs": [
            "lastNotNull"
          ],
          "fields": "",
          "values": false
        },
        "textMode": "value_and_name",
        "wideLayout": true
      }
    },
    {
      "id": 4,
      "type": "stat",
      "title": "Connected ASICs",
      "datasource": {
        "type": "prometheus",
        "uid": "bdag-prometheus"
      },
      "gridPos": {
        "x": 9,
        "y": 0,
        "w": 3,
        "h": 3
      },
      "targets": [
        {
          "expr": "bdag_miner_connected_count",
          "legendFormat": "",
          "refId": "A"
        }
      ],
      "fieldConfig": {
        "defaults": {
          "unit": "short",
          "custom": {},
          "color": {
            "mode": "thresholds"
          },
          "thresholds": {
            "mode": "absolute",
            "steps": [
              {
                "value": null,
                "color": "red"
              },
              {
                "value": 6,
                "color": "orange"
              },
              {
                "value": 7,
                "color": "green"
              }
            ]
          },
          "noValue": "-"
        },
        "overrides": []
      },
      "options": {
        "colorMode": "background",
        "graphMode": "none",
        "justifyMode": "center",
        "orientation": "auto",
        "reduceOptions": {
          "calcs": [
            "lastNotNull"
          ],
          "fields": "",
          "values": false
        },
        "textMode": "value_and_name",
        "wideLayout": true
      }
    },
    {
      "id": 5,
      "type": "stat",
      "title": "Node Lag",
      "datasource": {
        "type": "prometheus",
        "uid": "bdag-prometheus"
      },
      "gridPos": {
        "x": 12,
        "y": 0,
        "w": 3,
        "h": 3
      },
      "targets": [
        {
          "expr": "bdag_node_block_lag",
          "legendFormat": "",
          "refId": "A"
        }
      ],
      "fieldConfig": {
        "defaults": {
          "unit": "short",
          "custom": {},
          "color": {
            "mode": "thresholds"
          },
          "thresholds": {
            "mode": "absolute",
            "steps": [
              {
                "value": null,
                "color": "green"
              },
              {
                "value": 1,
                "color": "orange"
              },
              {
                "value": 5,
                "color": "red"
              }
            ]
          },
          "noValue": "-"
        },
        "overrides": []
      },
      "options": {
        "colorMode": "background",
        "graphMode": "none",
        "justifyMode": "center",
        "orientation": "auto",
        "reduceOptions": {
          "calcs": [
            "lastNotNull"
          ],
          "fields": "",
          "values": false
        },
        "textMode": "value_and_name",
        "wideLayout": true
      }
    },
    {
      "id": 6,
      "type": "stat",
      "title": "Share Age",
      "datasource": {
        "type": "prometheus",
        "uid": "bdag-prometheus"
      },
      "gridPos": {
        "x": 15,
        "y": 0,
        "w": 3,
        "h": 3
      },
      "targets": [
        {
          "expr": "bdag_pool_last_valid_share_age_seconds",
          "legendFormat": "",
          "refId": "A"
        }
      ],
      "fieldConfig": {
        "defaults": {
          "unit": "s",
          "custom": {},
          "color": {
            "mode": "thresholds"
          },
          "decimals": 0,
          "thresholds": {
            "mode": "absolute",
            "steps": [
              {
                "value": null,
                "color": "green"
              },
              {
                "value": 60,
                "color": "orange"
              },
              {
                "value": 180,
                "color": "red"
              }
            ]
          },
          "noValue": "-"
        },
        "overrides": []
      },
      "options": {
        "colorMode": "background",
        "graphMode": "none",
        "justifyMode": "center",
        "orientation": "auto",
        "reduceOptions": {
          "calcs": [
            "lastNotNull"
          ],
          "fields": "",
          "values": false
        },
        "textMode": "value_and_name",
        "wideLayout": true
      }
    },
    {
      "id": 7,
      "type": "stat",
      "title": "Submit OK",
      "datasource": {
        "type": "prometheus",
        "uid": "bdag-prometheus"
      },
      "gridPos": {
        "x": 18,
        "y": 0,
        "w": 3,
        "h": 3
      },
      "targets": [
        {
          "expr": "bdag_pool_block_submit_success_recent",
          "legendFormat": "",
          "refId": "A"
        }
      ],
      "fieldConfig": {
        "defaults": {
          "unit": "short",
          "custom": {},
          "color": {
            "mode": "thresholds"
          },
          "thresholds": {
            "mode": "absolute",
            "steps": [
              {
                "value": null,
                "color": "orange"
              },
              {
                "value": 1,
                "color": "green"
              }
            ]
          },
          "noValue": "-"
        },
        "overrides": []
      },
      "options": {
        "colorMode": "background",
        "graphMode": "none",
        "justifyMode": "center",
        "orientation": "auto",
        "reduceOptions": {
          "calcs": [
            "lastNotNull"
          ],
          "fields": "",
          "values": false
        },
        "textMode": "value_and_name",
        "wideLayout": true
      }
    },
    {
      "id": 8,
      "type": "stat",
      "title": "Submit Errors",
      "datasource": {
        "type": "prometheus",
        "uid": "bdag-prometheus"
      },
      "gridPos": {
        "x": 21,
        "y": 0,
        "w": 3,
        "h": 3
      },
      "targets": [
        {
          "expr": "bdag_pool_block_submit_error_recent",
          "legendFormat": "",
          "refId": "A"
        }
      ],
      "fieldConfig": {
        "defaults": {
          "unit": "short",
          "custom": {},
          "color": {
            "mode": "thresholds"
          },
          "thresholds": {
            "mode": "absolute",
            "steps": [
              {
                "value": null,
                "color": "green"
              },
              {
                "value": 1,
                "color": "orange"
              },
              {
                "value": 5,
                "color": "red"
              }
            ]
          },
          "noValue": "-"
        },
        "overrides": []
      },
      "options": {
        "colorMode": "background",
        "graphMode": "none",
        "justifyMode": "center",
        "orientation": "auto",
        "reduceOptions": {
          "calcs": [
            "lastNotNull"
          ],
          "fields": "",
          "values": false
        },
        "textMode": "value_and_name",
        "wideLayout": true
      }
    },
    {
      "id": 21,
      "type": "stat",
      "title": "Node Blocks",
      "datasource": {
        "type": "prometheus",
        "uid": "bdag-prometheus"
      },
      "gridPos": {
        "x": 0,
        "y": 3,
        "w": 8,
        "h": 4
      },
      "targets": [
        {
          "expr": "bdag_node_latest_block",
          "legendFormat": "",
          "refId": "A"
        }
      ],
      "fieldConfig": {
        "defaults": {
          "unit": "locale",
          "custom": {},
          "color": {
            "mode": "thresholds"
          },
          "decimals": 0,
          "noValue": "-"
        },
        "overrides": []
      },
      "options": {
        "colorMode": "background",
        "graphMode": "none",
        "justifyMode": "center",
        "orientation": "auto",
        "reduceOptions": {
          "calcs": [
            "lastNotNull"
          ],
          "fields": "",
          "values": false
        },
        "textMode": "value_and_name",
        "wideLayout": true
      }
    },
    {
      "id": 22,
      "type": "stat",
      "title": "Node Sync %",
      "datasource": {
        "type": "prometheus",
        "uid": "bdag-prometheus"
      },
      "gridPos": {
        "x": 8,
        "y": 3,
        "w": 8,
        "h": 4
      },
      "targets": [
        {
          "expr": "bdag_node_sync_progress_percent",
          "legendFormat": "",
          "refId": "A"
        }
      ],
      "fieldConfig": {
        "defaults": {
          "unit": "percent",
          "custom": {},
          "color": {
            "mode": "thresholds"
          },
          "decimals": 2,
          "noValue": "-"
        },
        "overrides": []
      },
      "options": {
        "colorMode": "background",
        "graphMode": "none",
        "justifyMode": "center",
        "orientation": "auto",
        "reduceOptions": {
          "calcs": [
            "lastNotNull"
          ],
          "fields": "",
          "values": false
        },
        "textMode": "value_and_name",
        "wideLayout": true
      }
    },
    {
      "id": 23,
      "type": "stat",
      "title": "Node Sync Gap",
      "datasource": {
        "type": "prometheus",
        "uid": "bdag-prometheus"
      },
      "gridPos": {
        "x": 16,
        "y": 3,
        "w": 8,
        "h": 4
      },
      "targets": [
        {
          "expr": "bdag_node_sync_remaining_blocks",
          "legendFormat": "",
          "refId": "A"
        }
      ],
      "fieldConfig": {
        "defaults": {
          "unit": "locale",
          "custom": {},
          "color": {
            "mode": "thresholds"
          },
          "decimals": 0,
          "thresholds": {
            "mode": "absolute",
            "steps": [
              {
                "value": null,
                "color": "green"
              },
              {
                "value": 1,
                "color": "orange"
              },
              {
                "value": 5,
                "color": "red"
              }
            ]
          },
          "noValue": "-"
        },
        "overrides": []
      },
      "options": {
        "colorMode": "background",
        "graphMode": "none",
        "justifyMode": "center",
        "orientation": "auto",
        "reduceOptions": {
          "calcs": [
            "lastNotNull"
          ],
          "fields": "",
          "values": false
        },
        "textMode": "value_and_name",
        "wideLayout": true
      }
    },
    {
      "id": 9,
      "type": "bargauge",
      "title": "Income By Miner - USD/h",
      "datasource": {
        "type": "prometheus",
        "uid": "bdag-prometheus"
      },
      "gridPos": {
        "x": 0,
        "y": 7,
        "w": 8,
        "h": 9
      },
      "targets": [
        {
          "expr": "sort_desc(bdag_miner_estimated_usd_per_hour)",
          "legendFormat": "{{miner}}",
          "refId": "A"
        }
      ],
      "fieldConfig": {
        "defaults": {
          "unit": "currencyUSD",
          "color": {
            "mode": "palette-classic"
          },
          "decimals": 2
        },
        "overrides": []
      },
      "options": {
        "displayMode": "gradient",
        "minVizHeight": 18,
        "minVizWidth": 0,
        "namePlacement": "left",
        "orientation": "horizontal",
        "reduceOptions": {
          "calcs": [
            "lastNotNull"
          ],
          "fields": "",
          "values": false
        },
        "showUnfilled": true,
        "sizing": "auto",
        "valueMode": "color"
      }
    },
    {
      "id": 10,
      "type": "bargauge",
      "title": "Accepted Work Share",
      "datasource": {
        "type": "prometheus",
        "uid": "bdag-prometheus"
      },
      "gridPos": {
        "x": 8,
        "y": 7,
        "w": 8,
        "h": 9
      },
      "targets": [
        {
          "expr": "sort_desc(bdag_miner_work_percent)",
          "legendFormat": "{{miner}}",
          "refId": "A"
        }
      ],
      "fieldConfig": {
        "defaults": {
          "unit": "percent",
          "color": {
            "mode": "palette-classic"
          },
          "decimals": 2
        },
        "overrides": []
      },
      "options": {
        "displayMode": "gradient",
        "minVizHeight": 18,
        "minVizWidth": 0,
        "namePlacement": "left",
        "orientation": "horizontal",
        "reduceOptions": {
          "calcs": [
            "lastNotNull"
          ],
          "fields": "",
          "values": false
        },
        "showUnfilled": true,
        "sizing": "auto",
        "valueMode": "color"
      }
    },
    {
      "id": 11,
      "type": "bargauge",
      "title": "Miner Freshness - Last Share Age",
      "datasource": {
        "type": "prometheus",
        "uid": "bdag-prometheus"
      },
      "gridPos": {
        "x": 16,
        "y": 7,
        "w": 8,
        "h": 9
      },
      "targets": [
        {
          "expr": "sort_desc(bdag_miner_last_share_age_seconds)",
          "legendFormat": "{{miner}}",
          "refId": "A"
        }
      ],
      "fieldConfig": {
        "defaults": {
          "unit": "s",
          "color": {
            "mode": "thresholds"
          },
          "decimals": 0,
          "thresholds": {
            "mode": "absolute",
            "steps": [
              {
                "value": null,
                "color": "green"
              },
              {
                "value": 60,
                "color": "orange"
              },
              {
                "value": 180,
                "color": "red"
              }
            ]
          }
        },
        "overrides": []
      },
      "options": {
        "displayMode": "gradient",
        "minVizHeight": 18,
        "minVizWidth": 0,
        "namePlacement": "left",
        "orientation": "horizontal",
        "reduceOptions": {
          "calcs": [
            "lastNotNull"
          ],
          "fields": "",
          "values": false
        },
        "showUnfilled": true,
        "sizing": "auto",
        "valueMode": "color"
      }
    },
    {
      "id": 12,
      "type": "timeseries",
      "title": "Revenue Velocity",
      "datasource": {
        "type": "prometheus",
        "uid": "bdag-prometheus"
      },
      "gridPos": {
        "x": 0,
        "y": 16,
        "w": 12,
        "h": 8
      },
      "maxDataPoints": 1200,
      "targets": [
        {
          "expr": "bdag_wallet_recent_usd_per_hour",
          "legendFormat": "wallet USD/h",
          "refId": "A",
          "interval": "$__interval"
        },
        {
          "expr": "bdag_wallet_recent_bdag_per_hour",
          "legendFormat": "wallet BDAG/h",
          "refId": "B",
          "interval": "$__interval"
        }
      ],
      "fieldConfig": {
        "defaults": {
          "unit": "short",
          "custom": {
            "drawStyle": "line",
            "lineInterpolation": "smooth",
            "lineWidth": 2,
            "fillOpacity": 12,
            "showPoints": "never",
            "spanNulls": true
          },
          "decimals": 2
        },
        "overrides": []
      },
      "options": {
        "legend": {
          "displayMode": "table",
          "placement": "bottom",
          "calcs": [
            "lastNotNull",
            "mean"
          ]
        },
        "tooltip": {
          "mode": "multi",
          "sort": "desc"
        }
      }
    },
    {
      "id": 13,
      "type": "timeseries",
      "title": "Per-Miner Income Trend",
      "datasource": {
        "type": "prometheus",
        "uid": "bdag-prometheus"
      },
      "gridPos": {
        "x": 12,
        "y": 16,
        "w": 12,
        "h": 8
      },
      "maxDataPoints": 1200,
      "targets": [
        {
          "expr": "bdag_miner_estimated_usd_per_hour",
          "legendFormat": "{{miner}}",
          "refId": "A",
          "interval": "$__interval"
        }
      ],
      "fieldConfig": {
        "defaults": {
          "unit": "currencyUSD",
          "custom": {
            "drawStyle": "line",
            "lineInterpolation": "smooth",
            "lineWidth": 2,
            "fillOpacity": 12,
            "showPoints": "never",
            "spanNulls": true
          },
          "decimals": 2
        },
        "overrides": []
      },
      "options": {
        "legend": {
          "displayMode": "table",
          "placement": "bottom",
          "calcs": [
            "lastNotNull",
            "mean"
          ]
        },
        "tooltip": {
          "mode": "multi",
          "sort": "desc"
        }
      }
    },
    {
      "id": 14,
      "type": "timeseries",
      "title": "Node Height And Import Health",
      "datasource": {
        "type": "prometheus",
        "uid": "bdag-prometheus"
      },
      "gridPos": {
        "x": 0,
        "y": 24,
        "w": 12,
        "h": 8
      },
      "maxDataPoints": 1200,
      "targets": [
        {
          "expr": "bdag_node_latest_block",
          "legendFormat": "{{node}} height",
          "refId": "A",
          "interval": "$__interval"
        },
        {
          "expr": "bdag_node_last_import_age_seconds",
          "legendFormat": "{{node}} import age",
          "refId": "B",
          "interval": "$__interval"
        }
      ],
      "fieldConfig": {
        "defaults": {
          "unit": "short",
          "custom": {
            "drawStyle": "line",
            "lineInterpolation": "smooth",
            "lineWidth": 2,
            "fillOpacity": 12,
            "showPoints": "never",
            "spanNulls": true
          }
        },
        "overrides": []
      },
      "options": {
        "legend": {
          "displayMode": "table",
          "placement": "bottom",
          "calcs": [
            "lastNotNull",
            "mean"
          ]
        },
        "tooltip": {
          "mode": "multi",
          "sort": "desc"
        }
      }
    },
    {
      "id": 15,
      "type": "timeseries",
      "title": "Pool Template Cadence",
      "datasource": {
        "type": "prometheus",
        "uid": "bdag-prometheus"
      },
      "gridPos": {
        "x": 12,
        "y": 24,
        "w": 12,
        "h": 8
      },
      "maxDataPoints": 1200,
      "targets": [
        {
          "expr": "bdag_pool_head_changes_recent",
          "legendFormat": "head changes",
          "refId": "A",
          "interval": "$__interval"
        },
        {
          "expr": "bdag_pool_job_notify_recent",
          "legendFormat": "job/diff pushes",
          "refId": "B",
          "interval": "$__interval"
        },
        {
          "expr": "bdag_pool_template_fetch_errors_recent",
          "legendFormat": "template errors",
          "refId": "C",
          "interval": "$__interval"
        }
      ],
      "fieldConfig": {
        "defaults": {
          "unit": "short",
          "custom": {
            "drawStyle": "line",
            "lineInterpolation": "smooth",
            "lineWidth": 2,
            "fillOpacity": 12,
            "showPoints": "never",
            "spanNulls": true
          }
        },
        "overrides": []
      },
      "options": {
        "legend": {
          "displayMode": "table",
          "placement": "bottom",
          "calcs": [
            "lastNotNull",
            "mean"
          ]
        },
        "tooltip": {
          "mode": "multi",
          "sort": "desc"
        }
      }
    },
    {
      "id": 16,
      "type": "timeseries",
      "title": "Block Submit Quality",
      "datasource": {
        "type": "prometheus",
        "uid": "bdag-prometheus"
      },
      "gridPos": {
        "x": 0,
        "y": 32,
        "w": 12,
        "h": 8
      },
      "maxDataPoints": 1200,
      "targets": [
        {
          "expr": "bdag_pool_block_submit_success_recent",
          "legendFormat": "success",
          "refId": "A",
          "interval": "$__interval"
        },
        {
          "expr": "bdag_pool_block_submit_error_recent",
          "legendFormat": "errors",
          "refId": "B",
          "interval": "$__interval"
        },
        {
          "expr": "bdag_pool_tip_overdue_recent",
          "legendFormat": "tip overdue",
          "refId": "C",
          "interval": "$__interval"
        },
        {
          "expr": "bdag_pool_duplicate_blocks_recent",
          "legendFormat": "duplicates",
          "refId": "D",
          "interval": "$__interval"
        }
      ],
      "fieldConfig": {
        "defaults": {
          "unit": "short",
          "custom": {
            "drawStyle": "line",
            "lineInterpolation": "smooth",
            "lineWidth": 2,
            "fillOpacity": 12,
            "showPoints": "never",
            "spanNulls": true
          }
        },
        "overrides": []
      },
      "options": {
        "legend": {
          "displayMode": "table",
          "placement": "bottom",
          "calcs": [
            "lastNotNull",
            "mean"
          ]
        },
        "tooltip": {
          "mode": "multi",
          "sort": "desc"
        }
      }
    },
    {
      "id": 17,
      "type": "timeseries",
      "title": "Global Pool Position",
      "datasource": {
        "type": "prometheus",
        "uid": "bdag-prometheus"
      },
      "gridPos": {
        "x": 12,
        "y": 32,
        "w": 12,
        "h": 8
      },
      "maxDataPoints": 1200,
      "targets": [
        {
          "expr": "bdag_global_pool_work_percent",
          "legendFormat": "{{pool}}",
          "refId": "A",
          "interval": "$__interval"
        }
      ],
      "fieldConfig": {
        "defaults": {
          "unit": "percent",
          "custom": {
            "drawStyle": "line",
            "lineInterpolation": "smooth",
            "lineWidth": 2,
            "fillOpacity": 12,
            "showPoints": "never",
            "spanNulls": true
          },
          "decimals": 2
        },
        "overrides": []
      },
      "options": {
        "legend": {
          "displayMode": "table",
          "placement": "bottom",
          "calcs": [
            "lastNotNull",
            "mean"
          ]
        },
        "tooltip": {
          "mode": "multi",
          "sort": "desc"
        }
      }
    },
    {
      "id": 18,
      "type": "table",
      "title": "Miner Operator Table",
      "datasource": {
        "type": "prometheus",
        "uid": "bdag-prometheus"
      },
      "gridPos": {
        "x": 0,
        "y": 40,
        "w": 12,
        "h": 8
      },
      "targets": [
        {
          "expr": "sort_desc(bdag_miner_estimated_usd_per_hour)",
          "legendFormat": "USD/h",
          "refId": "A",
          "instant": true,
          "format": "table"
        },
        {
          "expr": "sort_desc(bdag_miner_work_percent)",
          "legendFormat": "work %",
          "refId": "B",
          "instant": true,
          "format": "table"
        },
        {
          "expr": "sort_desc(bdag_miner_blocks_found_recent)",
          "legendFormat": "blocks found",
          "refId": "C",
          "instant": true,
          "format": "table"
        },
        {
          "expr": "sort_desc(bdag_miner_shares_recent)",
          "legendFormat": "shares",
          "refId": "D",
          "instant": true,
          "format": "table"
        }
      ],
      "fieldConfig": {
        "defaults": {
          "unit": "short"
        },
        "overrides": []
      },
      "options": {
        "cellHeight": "sm",
        "footer": {
          "show": false
        },
        "showHeader": true
      },
      "transformations": [
        {
          "id": "organize",
          "options": {
            "excludeByName": {
              "Time": true,
              "__name__": true,
              "instance": true,
              "job": true,
              "service": true,
              "ip": true,
              "mac": true
            },
            "renameByName": {
              "Value": "Value",
              "miner": "Miner",
              "node": "Node",
              "pool": "Pool"
            }
          }
        }
      ]
    },
    {
      "id": 19,
      "type": "table",
      "title": "Node And Pool Risk Table",
      "datasource": {
        "type": "prometheus",
        "uid": "bdag-prometheus"
      },
      "gridPos": {
        "x": 12,
        "y": 40,
        "w": 12,
        "h": 8
      },
      "targets": [
        {
          "expr": "bdag_node_last_import_age_seconds",
          "legendFormat": "node import age",
          "refId": "A",
          "instant": true,
          "format": "table"
        },
        {
          "expr": "bdag_node_p2p_stream_errors_recent",
          "legendFormat": "p2p stream errors",
          "refId": "B",
          "instant": true,
          "format": "table"
        },
        {
          "expr": "bdag_node_template_errors_recent",
          "legendFormat": "template errors",
          "refId": "C",
          "instant": true,
          "format": "table"
        },
        {
          "expr": "bdag_pool_last_valid_share_age_seconds",
          "legendFormat": "share age",
          "refId": "D",
          "instant": true,
          "format": "table"
        },
        {
          "expr": "bdag_pool_last_head_change_age_seconds",
          "legendFormat": "head age",
          "refId": "E",
          "instant": true,
          "format": "table"
        }
      ],
      "fieldConfig": {
        "defaults": {
          "unit": "short"
        },
        "overrides": []
      },
      "options": {
        "cellHeight": "sm",
        "footer": {
          "show": false
        },
        "showHeader": true
      },
      "transformations": [
        {
          "id": "organize",
          "options": {
            "excludeByName": {
              "Time": true,
              "__name__": true,
              "instance": true,
              "job": true,
              "service": true,
              "ip": true,
              "mac": true
            },
            "renameByName": {
              "Value": "Value",
              "miner": "Miner",
              "node": "Node",
              "pool": "Pool"
            }
          }
        }
      ]
    },
    {
      "id": 20,
      "type": "logs",
      "title": "Recent Mining Incidents",
      "datasource": {
        "type": "loki",
        "uid": "bdag-loki"
      },
      "gridPos": {
        "x": 0,
        "y": 48,
        "w": 24,
        "h": 10
      },
      "targets": [
        {
          "expr": "{job=~\"docker|bdag-runtime\"} |~ \"(ERROR|WARN|failed|degraded|repair|Block submission too late|template fetch error|miner)\"",
          "refId": "A"
        }
      ],
      "options": {
        "showTime": true,
        "showLabels": false,
        "wrapLogMessage": true,
        "sortOrder": "Descending"
      }
    }
  ]
}
